couture_cypher/__init__.py
couture_cypher/coutureCypher.py
CoutureCypher-0.0.2.dist-info/LICENSE
CoutureCypher-0.0.2.dist-info/METADATA
CoutureCypher-0.0.2.dist-info/WHEEL
CoutureCypher-0.0.2.dist-info/top_level.txt
CoutureCypher-0.0.2.dist-info/RECORD
