Metadata-Version: 2.1
Name: CoutureCypher
Version: 0.0.2
Summary: A Cypher
Author-email: Dominic Couture <d.paul.couture@gmail.com>
Project-URL: Homepage, https://github.com/mastermind-mayhem/CoutureCypher
Classifier: Programming Language :: Python :: 3
Classifier: License :: OSI Approved :: MIT License
Classifier: Operating System :: OS Independent
Requires-Python: >=3.9
License-File: LICENSE
